msg/__init__.py
msg/_image_tagging.py
msg/_ld_2d_bbox.py
msg/_ld_2d_bbox_list.py
msg/_ld_2d_instance_segmentation.py
msg/_ld_2d_polyline.py
msg/_ld_2d_polyline_list.py
msg/_ld_2dobject.py
msg/_ld_2dobject_list.py
msg/_ld_annotation_comment.py
msg/_ld_annotation_comment_item.py
msg/_ld_annotation_comment_list.py
msg/_ld_can.py
msg/_ld_can2.py
msg/_ld_data_msg.py
msg/_ld_ego_motion.py
msg/_ld_face.py
msg/_ld_gps.py
msg/_ld_image.py
msg/_ld_imu.py
msg/_ld_imu_gps.py
msg/_ld_imugps_can.py
msg/_ld_mesh.py
msg/_ld_mesh_list.py
msg/_ld_mobileye_lane.py
msg/_ld_mobileye_traffic_sign.py
msg/_ld_object.py
msg/_ld_object_list.py
msg/_ld_packet.py
msg/_ld_road_feature_facility.py
msg/_ld_road_feature_feature.py
msg/_ld_road_feature_lane.py
msg/_ld_road_feature_list.py
msg/_ld_rt_matrix.py
msg/_ld_sensor_location.py
ld_msgs-0.3.dist-info/METADATA
ld_msgs-0.3.dist-info/WHEEL
ld_msgs-0.3.dist-info/top_level.txt
ld_msgs-0.3.dist-info/RECORD
