Metadata-Version: 2.1
Name: ld-msgs
Version: 0.3
Summary: ld_msg lib for python
Home-page: 
Author: shuo shen
Author-email: shuo.shen@liangdao.de
Classifier: Development Status :: 3 - Alpha
Classifier: Intended Audience :: Developers
Classifier: License :: OSI Approved :: MIT License
Classifier: Programming Language :: Python :: 3
Classifier: Programming Language :: Python :: 3.7
Classifier: Programming Language :: Python :: 3.8
Classifier: Programming Language :: Python :: 3.10
Requires-Dist: genpy
